sqlmuggle/__init__.py
sqlmuggle/py.typed
sqlmuggle-0.0.1.dist-info/LICENSE
sqlmuggle-0.0.1.dist-info/METADATA
sqlmuggle-0.0.1.dist-info/WHEEL
sqlmuggle-0.0.1.dist-info/RECORD
